s3_file_picker/.gitignore
s3_file_picker/__init__.py
s3_file_picker/apps.py
s3_file_picker/models/__init__.py
s3_file_picker/models/field/S3KeyField.py
s3_file_picker/models/field/__init__.py
s3_file_picker/models/field/form/S3KeyForm.py
s3_file_picker/models/field/form/S3KeyInput.py
s3_file_picker/models/field/form/__init__.py
s3_file_picker/models/typed_dict/S3FileItem.py
s3_file_picker/models/typed_dict/S3FolderContent.py
s3_file_picker/models/typed_dict/__init__.py
s3_file_picker/service/S3Service.py
s3_file_picker/service/__init__.py
s3_file_picker/static/css/.gitkeep
s3_file_picker/static/css/filebrowser.css
s3_file_picker/static/js/.gitkeep
s3_file_picker/static/js/filebrowser.js
s3_file_picker/storage/AddressingStyle.py
s3_file_picker/storage/CustomS3Storage.py
s3_file_picker/storage/__init__.py
s3_file_picker/templates/s3_file_picker.html
s3_file_picker/templates/script.html
s3_file_picker/urls.py
s3_file_picker/view/FileView.py
s3_file_picker/view/FilesView.py
s3_file_picker/view/S3FilePickerWidget.py
s3_file_picker/view/__init__.py
django_s3_file_picker-0.1.1.dist-info/METADATA
django_s3_file_picker-0.1.1.dist-info/WHEEL
django_s3_file_picker-0.1.1.dist-info/RECORD
