Metadata-Version: 2.3
Name: django-s3-file-picker
Version: 0.1.1
Summary: Django S3 File Picker
License: MIT
Author: Николай Витальевич Никоноров
Author-email: nnv@bitt.moe
Requires-Python: >=3.10,<4.0
Classifier: License :: OSI Approved :: MIT License
Classifier: Programming Language :: Python :: 3
Classifier: Programming Language :: Python :: 3.10
Classifier: Programming Language :: Python :: 3.11
Classifier: Programming Language :: Python :: 3.12
Classifier: Programming Language :: Python :: 3.13
Requires-Dist: Django (==5.2.1)
Requires-Dist: boto3 (==1.38.15)
Requires-Dist: mypy-boto3-s3 (==1.38.0)
Project-URL: Repository, https://gitlab.com/Bitnik212/s3-file-picker
